mcmodmgr/__init__.py
mcmodmgr/_version.py
mcmodmgr/command.py
mcmodmgr/logging.py
mcmodmgr-0.1.0.dist-info/METADATA
mcmodmgr-0.1.0.dist-info/WHEEL
mcmodmgr-0.1.0.dist-info/entry_points.txt
mcmodmgr-0.1.0.dist-info/top_level.txt
mcmodmgr-0.1.0.dist-info/RECORD
